[
  {
    "title": "Bless your spouse out loud (one sentence)",
    "mode": "FAITH",
    "loveLanguage": "WORDS",
    "timeNeededMinutes": 2,
    "intimacyLevelMin": "PG",
    "seasonTags": [],
    "steps": ["Say one blessing over your spouse.", "End with: 'I'm on your side today.'"],
    "messageTemplate": "I'm blessing you today: _____. I'm on your side.",
    "whyItHelps": "Sets tone and unity with a quick faith-centered micro-ritual.",
    "pointsAwarded": 5
  },
  {
    "title": "7-minute couch talk (no screens)",
    "mode": "EMOTIONAL",
    "loveLanguage": "QUALITY_TIME",
    "timeNeededMinutes": 7,
    "intimacyLevelMin": "PG",
    "seasonTags": ["BUSY"],
    "steps": ["Set a 7-minute timer.", "Each share 1 win + 1 weight.", "End with: 'How can I support you?'"],
    "messageTemplate": "Can we do a 7-min couch talk tonight? No screens—just us.",
    "whyItHelps": "Creates emotional safety and connection in a doable timeframe.",
    "pointsAwarded": 7
  },
  {
    "title": "10-second hug at the door",
    "mode": "PHYSICAL",
    "loveLanguage": "TOUCH",
    "timeNeededMinutes": 2,
    "intimacyLevelMin": "PG",
    "seasonTags": [],
    "steps": ["Hug for 10 seconds.", "Breathe slowly together.", "Whisper: 'I missed you.'"],
    "messageTemplate": "When we see each other, can we do our 10-second hug?",
    "whyItHelps": "Small physical connection reduces stress and increases closeness.",
    "pointsAwarded": 5
  },
  {
    "title": "Do one helpful thing in 10 minutes",
    "mode": "ACTIONABLE",
    "loveLanguage": "ACTS",
    "timeNeededMinutes": 7,
    "intimacyLevelMin": "PG",
    "seasonTags": ["PARENTING_OVERLOAD"],
    "steps": ["Pick one small task your spouse dislikes.", "Do it now without announcing it.", "After, text: 'I took care of ____ for you.'"],
    "messageTemplate": "I'm handling ____ for you today 💛",
    "whyItHelps": "Practical support builds trust and reduces mental load.",
    "pointsAwarded": 7
  },
  {
    "title": "Send an encouraging voice message",
    "mode": "EMOTIONAL",
    "loveLanguage": "WORDS",
    "timeNeededMinutes": 2,
    "intimacyLevelMin": "PG",
    "seasonTags": [],
    "steps": ["Record a 30-second voice message.", "Share one thing you admire about them.", "Send it unexpectedly."],
    "messageTemplate": "Check your messages—I sent you something from the heart.",
    "whyItHelps": "Hearing your voice adds warmth that text can't capture.",
    "pointsAwarded": 5
  },
  {
    "title": "Pray together for 2 minutes",
    "mode": "FAITH",
    "loveLanguage": "ANY",
    "timeNeededMinutes": 2,
    "intimacyLevelMin": "PG",
    "seasonTags": [],
    "steps": ["Hold hands.", "One person prays for 1 minute.", "Switch. Keep it simple."],
    "messageTemplate": "Can we pray together for just 2 minutes tonight?",
    "whyItHelps": "Praying together builds spiritual intimacy like nothing else.",
    "pointsAwarded": 5
  },
  {
    "title": "Write a love note and hide it",
    "mode": "EMOTIONAL",
    "loveLanguage": "WORDS",
    "timeNeededMinutes": 2,
    "intimacyLevelMin": "PG",
    "seasonTags": [],
    "steps": ["Write 2-3 sentences on a sticky note.", "Hide it where they'll find it (wallet, mirror, lunch bag).", "Don't mention it—let them discover it."],
    "messageTemplate": null,
    "whyItHelps": "Surprise affirmation creates delight and shows intentionality.",
    "pointsAwarded": 5
  },
  {
    "title": "Give a 2-minute shoulder massage",
    "mode": "PHYSICAL",
    "loveLanguage": "TOUCH",
    "timeNeededMinutes": 2,
    "intimacyLevelMin": "PG",
    "seasonTags": ["STRESS"],
    "steps": ["Ask: 'Can I rub your shoulders for a couple minutes?'", "Focus on tension spots.", "Don't expect anything in return."],
    "messageTemplate": "Your shoulders look tense—let me help.",
    "whyItHelps": "Non-sexual touch shows care and helps them decompress.",
    "pointsAwarded": 5
  },
  {
    "title": "Pick up their favorite snack",
    "mode": "ACTIONABLE",
    "loveLanguage": "GIFTS",
    "timeNeededMinutes": 7,
    "intimacyLevelMin": "PG",
    "seasonTags": [],
    "steps": ["Think of their go-to comfort snack or drink.", "Pick it up on your way home.", "Leave it where they'll find it with a note."],
    "messageTemplate": "I got you something—check the counter 😊",
    "whyItHelps": "Small thoughtful gifts say 'I was thinking about you.'",
    "pointsAwarded": 7
  },
  {
    "title": "Compliment them in front of others",
    "mode": "EMOTIONAL",
    "loveLanguage": "WORDS",
    "timeNeededMinutes": 2,
    "intimacyLevelMin": "PG",
    "seasonTags": [],
    "steps": ["Next time you're with friends or family...", "Share something you appreciate about your spouse.", "Be specific and genuine."],
    "messageTemplate": null,
    "whyItHelps": "Public praise builds them up and shows you're proud of them.",
    "pointsAwarded": 5
  },
  {
    "title": "20-minute walk together",
    "mode": "PHYSICAL",
    "loveLanguage": "QUALITY_TIME",
    "timeNeededMinutes": 20,
    "intimacyLevelMin": "PG",
    "seasonTags": [],
    "steps": ["Put on shoes and go outside.", "Leave phones behind or on silent.", "Walk and talk—no agenda."],
    "messageTemplate": "Want to take a walk with me? Just us, no phones.",
    "whyItHelps": "Walking side-by-side naturally opens up conversation.",
    "pointsAwarded": 10
  },
  {
    "title": "Read a devotional together",
    "mode": "FAITH",
    "loveLanguage": "QUALITY_TIME",
    "timeNeededMinutes": 7,
    "intimacyLevelMin": "PG",
    "seasonTags": [],
    "steps": ["Pick a short couples devotional or Psalm.", "Read it aloud together.", "Share one takeaway each."],
    "messageTemplate": "Can we read something together tonight—just 7 minutes?",
    "whyItHelps": "Growing spiritually together strengthens your bond.",
    "pointsAwarded": 7
  },
  {
    "title": "Text 3 things you love about them",
    "mode": "EMOTIONAL",
    "loveLanguage": "WORDS",
    "timeNeededMinutes": 2,
    "intimacyLevelMin": "PG",
    "seasonTags": [],
    "steps": ["Think of 3 specific things you love.", "Text them one by one throughout the day.", "Be specific, not generic."],
    "messageTemplate": "Thing #1 I love about you today: ___",
    "whyItHelps": "Intentional affirmation fills their emotional tank.",
    "pointsAwarded": 5
  },
  {
    "title": "Cook their favorite meal together",
    "mode": "ACTIONABLE",
    "loveLanguage": "QUALITY_TIME",
    "timeNeededMinutes": 20,
    "intimacyLevelMin": "PG",
    "seasonTags": [],
    "steps": ["Pick a recipe they love.", "Cook it together—divide the tasks.", "Enjoy it together without screens."],
    "messageTemplate": "I want to cook your favorite meal together tonight. You in?",
    "whyItHelps": "Shared activities create memories and teamwork.",
    "pointsAwarded": 10
  },
  {
    "title": "Hold hands while watching TV",
    "mode": "PHYSICAL",
    "loveLanguage": "TOUCH",
    "timeNeededMinutes": 7,
    "intimacyLevelMin": "PG",
    "seasonTags": [],
    "steps": ["During your next show, reach for their hand.", "Just hold it—no phone in the other hand.", "Gentle squeezes say 'I'm here.'"],
    "messageTemplate": null,
    "whyItHelps": "Simple touch during routine activities maintains connection.",
    "pointsAwarded": 5
  },
  {
    "title": "Do their morning chore",
    "mode": "ACTIONABLE",
    "loveLanguage": "ACTS",
    "timeNeededMinutes": 7,
    "intimacyLevelMin": "PG",
    "seasonTags": ["BUSY"],
    "steps": ["Identify their usual morning task.", "Do it before they wake or get to it.", "Don't make a big deal—just do it."],
    "messageTemplate": "Good morning! One less thing on your plate today. 💛",
    "whyItHelps": "Starting their day lighter shows love through action.",
    "pointsAwarded": 7
  },
  {
    "title": "Pray for your spouse (silently)",
    "mode": "FAITH",
    "loveLanguage": "ANY",
    "timeNeededMinutes": 2,
    "intimacyLevelMin": "PG",
    "seasonTags": [],
    "steps": ["Take 2 minutes alone.", "Pray specifically for their current challenge.", "Text them: 'I just prayed for you.'"],
    "messageTemplate": "I just prayed for you and your [specific situation].",
    "whyItHelps": "Knowing someone is praying for you brings comfort and security.",
    "pointsAwarded": 5
  },
  {
    "title": "Plan a surprise date night",
    "mode": "ACTIONABLE",
    "loveLanguage": "QUALITY_TIME",
    "timeNeededMinutes": 20,
    "intimacyLevelMin": "PG",
    "seasonTags": [],
    "steps": ["Handle all logistics (babysitter, reservations, etc.).", "Keep it a surprise.", "Just tell them when to be ready."],
    "messageTemplate": "Clear your schedule for [date]—I've got plans for us.",
    "whyItHelps": "Taking initiative shows you prioritize the relationship.",
    "pointsAwarded": 10
  },
  {
    "title": "Give a genuine compliment about their appearance",
    "mode": "EMOTIONAL",
    "loveLanguage": "WORDS",
    "timeNeededMinutes": 2,
    "intimacyLevelMin": "PG",
    "seasonTags": [],
    "steps": ["Notice something specific.", "Tell them exactly what you like.", "Make eye contact when you say it."],
    "messageTemplate": null,
    "whyItHelps": "Feeling attractive to your spouse builds confidence and desire.",
    "pointsAwarded": 5
  },
  {
    "title": "Kiss for 6 seconds",
    "mode": "PHYSICAL",
    "loveLanguage": "TOUCH",
    "timeNeededMinutes": 2,
    "intimacyLevelMin": "ROMANTIC",
    "seasonTags": [],
    "steps": ["Before you leave or when you reunite...", "Kiss for a full 6 seconds.", "It's longer than you think—count it."],
    "messageTemplate": "6-second kiss when you get home?",
    "whyItHelps": "A 6-second kiss releases bonding chemicals and breaks routine.",
    "pointsAwarded": 5
  },
  {
    "title": "Order flowers or a small gift delivered",
    "mode": "ACTIONABLE",
    "loveLanguage": "GIFTS",
    "timeNeededMinutes": 7,
    "intimacyLevelMin": "PG",
    "seasonTags": [],
    "steps": ["Order something small online.", "Have it delivered to their work or home.", "Include a personal note."],
    "messageTemplate": "Something's coming your way... 💐",
    "whyItHelps": "Unexpected gifts say 'You're on my mind even when we're apart.'",
    "pointsAwarded": 7
  },
  {
    "title": "Say 'thank you' for something routine",
    "mode": "EMOTIONAL",
    "loveLanguage": "WORDS",
    "timeNeededMinutes": 2,
    "intimacyLevelMin": "PG",
    "seasonTags": [],
    "steps": ["Notice something they do regularly.", "Thank them specifically for it.", "Don't wait for big things—gratitude for small things matters."],
    "messageTemplate": "I don't say it enough, but thank you for always [specific thing].",
    "whyItHelps": "Gratitude prevents taking each other for granted.",
    "pointsAwarded": 5
  },
  {
    "title": "Listen without fixing",
    "mode": "EMOTIONAL",
    "loveLanguage": "QUALITY_TIME",
    "timeNeededMinutes": 7,
    "intimacyLevelMin": "PG",
    "seasonTags": ["STRESS"],
    "steps": ["Ask: 'Do you need me to listen or help solve?'", "If listen: just be present, no solutions.", "End with: 'That sounds hard. I'm here.'"],
    "messageTemplate": "I'm here to listen whenever you need to talk.",
    "whyItHelps": "Being heard without judgment is one of the deepest needs.",
    "pointsAwarded": 7
  },
  {
    "title": "Dance in the kitchen",
    "mode": "PHYSICAL",
    "loveLanguage": "TOUCH",
    "timeNeededMinutes": 2,
    "intimacyLevelMin": "PG",
    "seasonTags": [],
    "steps": ["Put on a favorite song.", "Pull them close and sway.", "Don't worry about steps—just be together."],
    "messageTemplate": "Dance with me? 🎶",
    "whyItHelps": "Playful physical connection breaks routine and creates joy.",
    "pointsAwarded": 5
  },
  {
    "title": "Take over bedtime routine",
    "mode": "ACTIONABLE",
    "loveLanguage": "ACTS",
    "timeNeededMinutes": 20,
    "intimacyLevelMin": "PG",
    "seasonTags": ["PARENTING_OVERLOAD"],
    "steps": ["Tell them: 'I've got the kids tonight.'", "Handle the full routine.", "Give them 20 minutes of peace."],
    "messageTemplate": "Go relax. I've got bedtime covered tonight.",
    "whyItHelps": "Giving rest is one of the best gifts for exhausted parents.",
    "pointsAwarded": 10
  },
  {
    "title": "Share a Scripture that encouraged you",
    "mode": "FAITH",
    "loveLanguage": "WORDS",
    "timeNeededMinutes": 2,
    "intimacyLevelMin": "PG",
    "seasonTags": [],
    "steps": ["Find a verse that spoke to you recently.", "Share it with your spouse.", "Explain briefly why it matters to you."],
    "messageTemplate": "This verse hit me today: ___. Made me think of us.",
    "whyItHelps": "Sharing spiritual insights deepens intimacy.",
    "pointsAwarded": 5
  },
  {
    "title": "Put your phone away for dinner",
    "mode": "EMOTIONAL",
    "loveLanguage": "QUALITY_TIME",
    "timeNeededMinutes": 20,
    "intimacyLevelMin": "PG",
    "seasonTags": [],
    "steps": ["Put phones in another room—both of you.", "Eat together with full attention.", "Ask one meaningful question."],
    "messageTemplate": "Phone-free dinner tonight? I want to really be present.",
    "whyItHelps": "Undivided attention shows your spouse they're the priority.",
    "pointsAwarded": 10
  },
  {
    "title": "Cuddle for 7 minutes before sleep",
    "mode": "PHYSICAL",
    "loveLanguage": "TOUCH",
    "timeNeededMinutes": 7,
    "intimacyLevelMin": "ROMANTIC",
    "seasonTags": [],
    "steps": ["Get in bed a few minutes early.", "Cuddle close—no phones.", "Just be present together."],
    "messageTemplate": "Can we cuddle before we fall asleep tonight?",
    "whyItHelps": "Physical closeness at day's end reinforces security.",
    "pointsAwarded": 7
  },
  {
    "title": "Fill up their gas tank",
    "mode": "ACTIONABLE",
    "loveLanguage": "ACTS",
    "timeNeededMinutes": 7,
    "intimacyLevelMin": "PG",
    "seasonTags": [],
    "steps": ["Take their car.", "Fill the tank and maybe wash it.", "Return it without saying anything."],
    "messageTemplate": "Noticed your tank was low—taken care of!",
    "whyItHelps": "Practical care removes stress from their day.",
    "pointsAwarded": 7
  },
  {
    "title": "Frame a photo of you two",
    "mode": "ACTIONABLE",
    "loveLanguage": "GIFTS",
    "timeNeededMinutes": 20,
    "intimacyLevelMin": "PG",
    "seasonTags": [],
    "steps": ["Pick a favorite photo together.", "Get it printed and framed.", "Place it somewhere visible."],
    "messageTemplate": "I found a photo of us I love. Framing it for us.",
    "whyItHelps": "Visual reminders of happy times strengthen your bond.",
    "pointsAwarded": 10
  },
  {
    "title": "Send a midday 'thinking of you' text",
    "mode": "EMOTIONAL",
    "loveLanguage": "WORDS",
    "timeNeededMinutes": 2,
    "intimacyLevelMin": "PG",
    "seasonTags": ["BUSY"],
    "steps": ["Set a reminder for midday.", "Send a simple 'thinking about you' message.", "Be specific if you can."],
    "messageTemplate": "Random thought: I'm really glad I married you.",
    "whyItHelps": "Small touchpoints throughout the day maintain connection.",
    "pointsAwarded": 5
  },
  {
    "title": "Ask about their dream or goal",
    "mode": "EMOTIONAL",
    "loveLanguage": "QUALITY_TIME",
    "timeNeededMinutes": 7,
    "intimacyLevelMin": "PG",
    "seasonTags": [],
    "steps": ["Ask: 'Is there a dream you've been thinking about lately?'", "Listen fully without judgment.", "Ask follow-up questions."],
    "messageTemplate": "I'd love to hear about something you've been dreaming about.",
    "whyItHelps": "Showing interest in their inner world builds deep connection.",
    "pointsAwarded": 7
  },
  {
    "title": "Initiate a back scratch session",
    "mode": "PHYSICAL",
    "loveLanguage": "TOUCH",
    "timeNeededMinutes": 7,
    "intimacyLevelMin": "PG",
    "seasonTags": [],
    "steps": ["Offer to scratch their back.", "Take your time—no rushing.", "Let them relax completely."],
    "messageTemplate": "Back scratch while we watch TV?",
    "whyItHelps": "Gentle, sustained touch helps both of you unwind.",
    "pointsAwarded": 5
  },
  {
    "title": "Make them coffee/tea in the morning",
    "mode": "ACTIONABLE",
    "loveLanguage": "ACTS",
    "timeNeededMinutes": 2,
    "intimacyLevelMin": "PG",
    "seasonTags": [],
    "steps": ["Wake up a bit early.", "Make their morning beverage just how they like it.", "Bring it to them."],
    "messageTemplate": null,
    "whyItHelps": "Starting their day with a small act of service sets a loving tone.",
    "pointsAwarded": 5
  },
  {
    "title": "Create a playlist for them",
    "mode": "ACTIONABLE",
    "loveLanguage": "GIFTS",
    "timeNeededMinutes": 20,
    "intimacyLevelMin": "PG",
    "seasonTags": [],
    "steps": ["Think about songs that remind you of them or your relationship.", "Create a playlist with 10-15 songs.", "Share it with a note explaining why."],
    "messageTemplate": "Made you something—a playlist of songs that remind me of us.",
    "whyItHelps": "Music carries emotion; a curated playlist is deeply personal.",
    "pointsAwarded": 10
  },
  {
    "title": "Speak their love language today",
    "mode": "EMOTIONAL",
    "loveLanguage": "ANY",
    "timeNeededMinutes": 7,
    "intimacyLevelMin": "PG",
    "seasonTags": [],
    "steps": ["Identify their primary love language.", "Do one intentional thing in that language today.", "Watch their response."],
    "messageTemplate": "I'm making an effort to speak your language today. Notice anything?",
    "whyItHelps": "Speaking their language fills their tank most effectively.",
    "pointsAwarded": 7
  },
  {
    "title": "Confess and ask for forgiveness",
    "mode": "FAITH",
    "loveLanguage": "ANY",
    "timeNeededMinutes": 7,
    "intimacyLevelMin": "PG",
    "seasonTags": ["CONFLICT"],
    "steps": ["Identify something you need to own.", "Say: 'I was wrong when I ___. Will you forgive me?'", "Don't add excuses or 'but...'"],
    "messageTemplate": null,
    "whyItHelps": "Humility and ownership heal wounds and build trust.",
    "pointsAwarded": 7
  },
  {
    "title": "Foot rub while talking",
    "mode": "PHYSICAL",
    "loveLanguage": "TOUCH",
    "timeNeededMinutes": 7,
    "intimacyLevelMin": "PG",
    "seasonTags": [],
    "steps": ["Ask about their day.", "While they talk, rub their feet.", "Focus on them—not the TV."],
    "messageTemplate": "Tell me about your day while I rub your feet.",
    "whyItHelps": "Combines physical touch with quality attention.",
    "pointsAwarded": 7
  },
  {
    "title": "Handle a task they've been putting off",
    "mode": "ACTIONABLE",
    "loveLanguage": "ACTS",
    "timeNeededMinutes": 20,
    "intimacyLevelMin": "PG",
    "seasonTags": [],
    "steps": ["Notice something on their mental to-do list.", "Handle it without being asked.", "Let them know when it's done."],
    "messageTemplate": "That thing you've been meaning to do? Done. 💪",
    "whyItHelps": "Removing mental load is one of the most loving acts of service.",
    "pointsAwarded": 10
  },
  {
    "title": "Buy them a book they'd enjoy",
    "mode": "ACTIONABLE",
    "loveLanguage": "GIFTS",
    "timeNeededMinutes": 7,
    "intimacyLevelMin": "PG",
    "seasonTags": [],
    "steps": ["Think about their interests or something they mentioned.", "Order or buy a book related to it.", "Gift it with a personal note inside."],
    "messageTemplate": "Got you something to read—made me think of you.",
    "whyItHelps": "Thoughtful gifts show you pay attention to who they are.",
    "pointsAwarded": 7
  },
  {
    "title": "Share a childhood memory",
    "mode": "EMOTIONAL",
    "loveLanguage": "QUALITY_TIME",
    "timeNeededMinutes": 7,
    "intimacyLevelMin": "PG",
    "seasonTags": [],
    "steps": ["Share a memory from your childhood.", "Explain why it shaped you.", "Ask them to share one too."],
    "messageTemplate": "I want to tell you about something from when I was a kid...",
    "whyItHelps": "Sharing history builds deeper understanding and intimacy.",
    "pointsAwarded": 7
  },
  {
    "title": "Give a forehead kiss",
    "mode": "PHYSICAL",
    "loveLanguage": "TOUCH",
    "timeNeededMinutes": 2,
    "intimacyLevelMin": "PG",
    "seasonTags": [],
    "steps": ["When they're focused on something...", "Gently kiss their forehead.", "Say nothing—just that."],
    "messageTemplate": null,
    "whyItHelps": "Forehead kisses feel protective and tender.",
    "pointsAwarded": 5
  },
  {
    "title": "Write out your wedding vows (or what you'd say now)",
    "mode": "FAITH",
    "loveLanguage": "WORDS",
    "timeNeededMinutes": 20,
    "intimacyLevelMin": "PG",
    "seasonTags": [],
    "steps": ["Write what you'd promise your spouse today.", "Be honest and specific.", "Share it with them in a quiet moment."],
    "messageTemplate": "I wrote something for you. Can I share it?",
    "whyItHelps": "Renewing commitment in words strengthens your covenant.",
    "pointsAwarded": 10
  },
  {
    "title": "Plan a getaway (even just overnight)",
    "mode": "ACTIONABLE",
    "loveLanguage": "QUALITY_TIME",
    "timeNeededMinutes": 20,
    "intimacyLevelMin": "PG",
    "seasonTags": [],
    "steps": ["Research a simple overnight option.", "Handle logistics (childcare, booking).", "Surprise them with the plan."],
    "messageTemplate": "I'm planning something for us. Pack a bag for [date].",
    "whyItHelps": "Dedicated couple time away reconnects you on multiple levels.",
    "pointsAwarded": 10
  },
  {
    "title": "Flirty text during the day",
    "mode": "EMOTIONAL",
    "loveLanguage": "WORDS",
    "timeNeededMinutes": 2,
    "intimacyLevelMin": "ROMANTIC",
    "seasonTags": [],
    "steps": ["Send something playful and flirty.", "Keep it honoring but spicy.", "Let anticipation build."],
    "messageTemplate": "I can't stop thinking about you... 😏",
    "whyItHelps": "Flirting keeps romance alive outside the bedroom.",
    "pointsAwarded": 5
  },
  {
    "title": "Initiate intimate connection tonight",
    "mode": "PHYSICAL",
    "loveLanguage": "TOUCH",
    "timeNeededMinutes": 20,
    "intimacyLevelMin": "MARRIED",
    "seasonTags": [],
    "steps": ["Create the right atmosphere.", "Initiate gently and attentively.", "Focus on them, not just the act."],
    "messageTemplate": "I'd love to be close to you tonight...",
    "whyItHelps": "Intentional intimacy strengthens your physical and emotional bond.",
    "pointsAwarded": 10
  },
  {
    "title": "Recall your first date",
    "mode": "EMOTIONAL",
    "loveLanguage": "QUALITY_TIME",
    "timeNeededMinutes": 7,
    "intimacyLevelMin": "PG",
    "seasonTags": [],
    "steps": ["Sit together and remember your first date.", "Share what you were thinking/feeling.", "Laugh at the memories."],
    "messageTemplate": "Remember our first date? Let's talk about it tonight.",
    "whyItHelps": "Revisiting your story reinforces your bond and shared history.",
    "pointsAwarded": 7
  },
  {
    "title": "Say 'I love you' with eye contact",
    "mode": "EMOTIONAL",
    "loveLanguage": "WORDS",
    "timeNeededMinutes": 2,
    "intimacyLevelMin": "PG",
    "seasonTags": [],
    "steps": ["Stop what you're doing.", "Look into their eyes.", "Say 'I love you' slowly and meaningfully."],
    "messageTemplate": null,
    "whyItHelps": "Intentional eye contact makes familiar words feel new.",
    "pointsAwarded": 5
  },
  {
    "title": "Sensual massage",
    "mode": "PHYSICAL",
    "loveLanguage": "TOUCH",
    "timeNeededMinutes": 20,
    "intimacyLevelMin": "MARRIED",
    "seasonTags": [],
    "steps": ["Set the mood with candles or music.", "Use lotion or oil.", "Focus on making them feel good."],
    "messageTemplate": "Let me take care of you tonight...",
    "whyItHelps": "Intentional physical care builds trust and desire.",
    "pointsAwarded": 10
  },
  {
    "title": "Ask: 'How can I love you better?'",
    "mode": "EMOTIONAL",
    "loveLanguage": "QUALITY_TIME",
    "timeNeededMinutes": 7,
    "intimacyLevelMin": "PG",
    "seasonTags": [],
    "steps": ["Find a calm moment.", "Ask: 'How can I love you better right now?'", "Listen without defending."],
    "messageTemplate": "I want to love you well. How can I do better?",
    "whyItHelps": "Asking shows humility and commitment to growth.",
    "pointsAwarded": 7
  },
  {
    "title": "Surprise breakfast in bed",
    "mode": "ACTIONABLE",
    "loveLanguage": "ACTS",
    "timeNeededMinutes": 20,
    "intimacyLevelMin": "PG",
    "seasonTags": [],
    "steps": ["Wake up a bit early.", "Make their favorite breakfast.", "Bring it to them in bed."],
    "messageTemplate": null,
    "whyItHelps": "Starting the day being served feels special and loved.",
    "pointsAwarded": 10
  },
  {
    "title": "Give them your undivided attention for 20 minutes",
    "mode": "EMOTIONAL",
    "loveLanguage": "QUALITY_TIME",
    "timeNeededMinutes": 20,
    "intimacyLevelMin": "PG",
    "seasonTags": [],
    "steps": ["Put away all devices.", "Face them and be fully present.", "Ask questions, listen, engage."],
    "messageTemplate": "I want to give you my full attention tonight. 20 minutes, just us.",
    "whyItHelps": "Undivided attention in a distracted world is rare and valuable.",
    "pointsAwarded": 10
  },
  {
    "title": "Speak a blessing over your home",
    "mode": "FAITH",
    "loveLanguage": "ANY",
    "timeNeededMinutes": 2,
    "intimacyLevelMin": "PG",
    "seasonTags": [],
    "steps": ["Walk through your home together (or alone).", "Pray a blessing over each room.", "Declare peace, love, and God's presence."],
    "messageTemplate": "Let's pray over our home together.",
    "whyItHelps": "Spiritual covering over your home sets the atmosphere.",
    "pointsAwarded": 5
  },
  {
    "title": "Send a GIF that reminds you of them",
    "mode": "EMOTIONAL",
    "loveLanguage": "WORDS",
    "timeNeededMinutes": 2,
    "intimacyLevelMin": "PG",
    "seasonTags": [],
    "steps": ["Find a funny or sweet GIF.", "Send it with 'This reminded me of you because...'"],
    "messageTemplate": null,
    "whyItHelps": "Playful communication keeps things light and fun.",
    "pointsAwarded": 5
  },
  {
    "title": "Sit close during movie night",
    "mode": "PHYSICAL",
    "loveLanguage": "TOUCH",
    "timeNeededMinutes": 7,
    "intimacyLevelMin": "PG",
    "seasonTags": [],
    "steps": ["During the movie, sit touching.", "Hold hands, put arm around them, or cuddle.", "Stay physically connected throughout."],
    "messageTemplate": "Movie night? I want to cuddle up with you.",
    "whyItHelps": "Maintaining touch during shared activities deepens connection.",
    "pointsAwarded": 5
  },
  {
    "title": "Research a topic they're interested in",
    "mode": "ACTIONABLE",
    "loveLanguage": "QUALITY_TIME",
    "timeNeededMinutes": 20,
    "intimacyLevelMin": "PG",
    "seasonTags": [],
    "steps": ["Think of something they love that you don't know much about.", "Spend time learning about it.", "Ask them questions or share what you learned."],
    "messageTemplate": "I learned something about [their interest] today. Can I tell you?",
    "whyItHelps": "Entering their world shows you value who they are.",
    "pointsAwarded": 10
  },
  {
    "title": "Date night at home (candles + intentionality)",
    "mode": "EMOTIONAL",
    "loveLanguage": "QUALITY_TIME",
    "timeNeededMinutes": 20,
    "intimacyLevelMin": "ROMANTIC",
    "seasonTags": ["BUSY", "PARENTING_OVERLOAD"],
    "steps": ["After kids are in bed, light candles.", "Put on soft music.", "Talk, connect, just be together."],
    "messageTemplate": "Homemade date night tonight? Candles, music, just us.",
    "whyItHelps": "Intentionality transforms ordinary evenings into connection.",
    "pointsAwarded": 10
  },
  {
    "title": "Express physical desire (with words)",
    "mode": "PHYSICAL",
    "loveLanguage": "WORDS",
    "timeNeededMinutes": 2,
    "intimacyLevelMin": "MARRIED",
    "seasonTags": [],
    "steps": ["Tell your spouse you find them attractive.", "Be specific about what you desire.", "Let them feel wanted."],
    "messageTemplate": "You should know... I really want you.",
    "whyItHelps": "Verbal desire makes your spouse feel wanted and desirable.",
    "pointsAwarded": 5
  }
]
